{
  "status": 0,
  "message": [
    {
      "id": 3,
      "title": "测试数据2群体",
      "img_url": "../../../data/测试.jpg",
      "summary": "测试一下"
    },
    {
      "id": 4,
      "title": "测试数据",
      "img_url": "../../../data/测试.jpg",
      "summary": "测试一下"
    },
    {
      "id": 5,
      "title": "测试数据",
      "img_url": "../../../data/测试.jpg",
      "summary": "测试一下"
    },
    {
      "id": 4,
      "title": "测试数据",
      "img_url": "../../../data/测试.jpg",
      "summary": "测试一下"
    }
  ]
}